README.md
setup.py
moz_crlite_lib/__init__.py
moz_crlite_lib/crlite_lib_test.py
moz_crlite_lib.egg-info/PKG-INFO
moz_crlite_lib.egg-info/SOURCES.txt
moz_crlite_lib.egg-info/dependency_links.txt
moz_crlite_lib.egg-info/top_level.txt
moz_crlite_lib.egg-info/zip-safe