Metadata-Version: 1.1
Name: moz-crlite-lib
Version: 0.2
Summary: Formats and tools used for CRLite
Home-page: http://github.com/mozilla/crlite
Author: J.C. Jones
Author-email: jc@mozilla.com
License: Mozilla Public License 2.0 (MPL 2.0)
Keywords: bloom filter cascade multi level mlbf crlite
Platform: UNKNOWN
Classifier: Development Status :: 4 - Beta
Classifier: License :: OSI Approved :: Mozilla Public License 2.0 (MPL 2.0)
Classifier: Programming Language :: Python :: 3
